modeled_metrics_monitoring/__init__.py
modeled_metrics_monitoring/config.py
modeled_metrics_monitoring/decorators.py
modeled_metrics_monitoring/metric_descriptor.py
modeled_metrics_monitoring/metric_writer.py
modeled_metrics_monitoring/utils.py
unacast_modeled_metrics_monitoring-0.1.1.dist-info/licenses/LICENSE
unacast_modeled_metrics_monitoring-0.1.1.dist-info/METADATA
unacast_modeled_metrics_monitoring-0.1.1.dist-info/WHEEL
unacast_modeled_metrics_monitoring-0.1.1.dist-info/top_level.txt
unacast_modeled_metrics_monitoring-0.1.1.dist-info/RECORD
