Metadata-Version: 2.4
Name: unacast-modeled-metrics-monitoring
Version: 0.1.1
Summary: A library for monitoring modeled metrics with Google Cloud Monitoring
Author-email: Jan Hajny <jan.hajny@unacast.com>
Requires-Python: >=3.8
License-File: LICENSE
Requires-Dist: google-auth>=2.24.0
Requires-Dist: google-cloud-monitoring>=2.0.0
Requires-Dist: google-cloud-resource-manager>=1.14.2
Requires-Dist: PyYAML>=6.0
Requires-Dist: requests>=2.32.0
Provides-Extra: dev
Requires-Dist: pytest>=7.0.0; extra == "dev"
Requires-Dist: black>=23.0.0; extra == "dev"
Requires-Dist: flake8>=6.0.0; extra == "dev"
Requires-Dist: mypy>=1.0.0; extra == "dev"
Requires-Dist: isort>=5.12.0; extra == "dev"
Requires-Dist: autopep8>=2.0.0; extra == "dev"
Requires-Dist: types-PyYAML>=6.0.0; extra == "dev"
Requires-Dist: types-requests>=2.32.0; extra == "dev"
Requires-Dist: tomli-w>=1.0.0; extra == "dev"
Dynamic: license-file
